eezo/__init__.py
eezo/client.py
eezo/errors.py
eezo/state.py
eezo/agent/__init__.py
eezo/agent/agent.py
eezo/agent/agents.py
eezo/interface/__init__.py
eezo/interface/context.py
eezo/interface/message.py
eezo/interface/components/__init__.py
eezo/interface/components/chart.py
eezo/interface/components/component.py
eezo/interface/components/image.py
eezo/interface/components/text.py
eezo/interface/components/youtube_video.py
eezo-0.4.1.dist-info/METADATA
eezo-0.4.1.dist-info/WHEEL
eezo-0.4.1.dist-info/top_level.txt
eezo-0.4.1.dist-info/RECORD
