Metadata-Version: 2.1
Name: eezo
Version: 0.4.1
Summary: Eezo helps you to build and supervise your AI agent workforce.
Home-page: UNKNOWN
Author: Daniel Schoenbohm
Author-email: daniel@eezo.ai
License: UNKNOWN
Platform: UNKNOWN
Classifier: Development Status :: 3 - Alpha
Classifier: Intended Audience :: Developers
Classifier: Natural Language :: English
Classifier: Operating System :: OS Independent
Classifier: Programming Language :: Python
Classifier: Programming Language :: Python :: 3
Classifier: Programming Language :: Python :: 3.6
Classifier: Programming Language :: Python :: 3.7
Classifier: Programming Language :: Python :: 3.8
Classifier: Programming Language :: Python :: 3.9
Classifier: Programming Language :: Python :: 3.10
Classifier: Programming Language :: Python :: 3.11
Classifier: Topic :: Software Development :: Libraries :: Python Modules
Classifier: Topic :: Utilities
Requires-Dist: annotated-types (==0.6.0)
Requires-Dist: bidict (==0.23.1)
Requires-Dist: certifi (==2024.2.2)
Requires-Dist: charset-normalizer (==3.3.2)
Requires-Dist: h11 (==0.14.0)
Requires-Dist: idna (==3.7)
Requires-Dist: pydantic (==2.7.1)
Requires-Dist: pydantic-core (==2.18.2)
Requires-Dist: python-dotenv (==1.0.1)
Requires-Dist: python-engineio (==4.9.0)
Requires-Dist: python-socketio (==5.11.2)
Requires-Dist: requests (==2.31.0)
Requires-Dist: simple-websocket (==1.0.0)
Requires-Dist: typing-extensions (==4.11.0)
Requires-Dist: urllib3 (==2.2.1)
Requires-Dist: watchdog (==4.0.0)
Requires-Dist: websocket-client (==1.8.0)
Requires-Dist: wsproto (==1.2.0)
